prefetch.py
django_prefetch-1.2.3.dist-info/AUTHORS.rst
django_prefetch-1.2.3.dist-info/LICENSE
django_prefetch-1.2.3.dist-info/METADATA
django_prefetch-1.2.3.dist-info/WHEEL
django_prefetch-1.2.3.dist-info/top_level.txt
django_prefetch-1.2.3.dist-info/RECORD
